rxnutils/__init__.py
rxnutils/chem/__init__.py
rxnutils/chem/augmentation.py
rxnutils/chem/cgr.py
rxnutils/chem/disconnection_sites/atom_map_tagging.py
rxnutils/chem/disconnection_sites/tag_converting.py
rxnutils/chem/features/__init__.py
rxnutils/chem/features/reaction_centre_fp.py
rxnutils/chem/features/rxnfp_runner.py
rxnutils/chem/features/sc_score.py
rxnutils/chem/features/simple_rdkit.py
rxnutils/chem/protection/__init__.py
rxnutils/chem/protection/amino_acids.py
rxnutils/chem/reaction.py
rxnutils/chem/rinchi/__init__.py
rxnutils/chem/rinchi/download_rinchi.py
rxnutils/chem/rinchi/rinchi_api.py
rxnutils/chem/smartslib.py
rxnutils/chem/template.py
rxnutils/chem/utils.py
rxnutils/data/__init__.py
rxnutils/data/base_pipeline.py
rxnutils/data/batch_utils.py
rxnutils/data/clean_pipeline.yml
rxnutils/data/mapping.py
rxnutils/data/mapping_pipeline.py
rxnutils/data/ord/README.md
rxnutils/data/ord/__init__.py
rxnutils/data/ord/import_ord_dataset.py
rxnutils/data/ord/preparation_pipeline.py
rxnutils/data/uspto/README.md
rxnutils/data/uspto/__init__.py
rxnutils/data/uspto/combine.py
rxnutils/data/uspto/download.py
rxnutils/data/uspto/preparation_pipeline.py
rxnutils/data/uspto/uspto_yield.py
rxnutils/pipeline/__init__.py
rxnutils/pipeline/actions/__init__.py
rxnutils/pipeline/actions/dataframe_mod.py
rxnutils/pipeline/actions/reaction_mod.py
rxnutils/pipeline/actions/reaction_props.py
rxnutils/pipeline/actions/templates.py
rxnutils/pipeline/base.py
rxnutils/pipeline/runner.py
rxnutils/routes/__init__.py
rxnutils/routes/base.py
rxnutils/routes/chemformer_feasibility/__init__.py
rxnutils/routes/chemformer_feasibility/model_interface.py
rxnutils/routes/chemformer_feasibility/scoring.py
rxnutils/routes/comparison.py
rxnutils/routes/deepset/__init__.py
rxnutils/routes/deepset/featurizers.py
rxnutils/routes/deepset/scoring.py
rxnutils/routes/image.py
rxnutils/routes/readers.py
rxnutils/routes/retro_bleu/__init__.py
rxnutils/routes/retro_bleu/ngram_collection.py
reaction_utils-1.9.3.dist-info/METADATA
reaction_utils-1.9.3.dist-info/WHEEL
reaction_utils-1.9.3.dist-info/licenses/LICENSE
reaction_utils-1.9.3.dist-info/RECORD
