Metadata-Version: 2.4
Name: reaction_utils
Version: 1.9.3
Summary: Utilities for working with reactions, reaction templates and template extraction
License: Apache-2.0
License-File: LICENSE
Author: Genheden, Samuel
Author-email: samuel.genheden@astrazeneca.com
Requires-Python: >=3.9,<3.13
Classifier: License :: OSI Approved :: Apache Software License
Classifier: Programming Language :: Python :: 3
Classifier: Programming Language :: Python :: 3.9
Classifier: Programming Language :: Python :: 3.10
Classifier: Programming Language :: Python :: 3.11
Classifier: Programming Language :: Python :: 3.12
Provides-Extra: models
Requires-Dist: Deprecated (>=1.2.13,<2.0.0)
Requires-Dist: PyYAML (>=6.0.1,<7.0.0)
Requires-Dist: apted (>=1.0.3,<2.0.0)
Requires-Dist: cgrtools-plus (>=4.1.35,<5.0.0)
Requires-Dist: dask (>=2024.4.1)
Requires-Dist: metaflow (>=2.6.3,<3.0.0)
Requires-Dist: numpy (>=1.0.0,<2.0.0)
Requires-Dist: onnxruntime (<1.17.0) ; extra == "models"
Requires-Dist: pandas (>=1.0.0,<3.0.0)
Requires-Dist: py7zr (>=1.0.0,<2.0.0)
Requires-Dist: pydantic (>=2.8.2,<3.0.0)
Requires-Dist: rdchiral (>=1.1.0,<2.0.0)
Requires-Dist: rdkit (>=2023.9.1,<2024.0.0)
Requires-Dist: scipy (>=1.11.4,<2.0.0)
Requires-Dist: swifter (>=1.0.9,<2.0.0)
Requires-Dist: urllib3 (>=1.2.26,<2.0.0)
Requires-Dist: wrapt-timeout-decorator (>=1.3.12,<2.0.0)
Requires-Dist: xxhash (>=3.0.0,<4.0.0)
Project-URL: Documentation, https://molecularai.github.io/reaction_utils/
Project-URL: Homepage, https://github.com/MolecularAI/reaction_utils/
Project-URL: Repository, https://github.com/MolecularAI/reaction_utils/
